{
  "todo": [
    {
      "name": "asdf asdf as df asdf asd fasd fas dfas dfas dfasd fas df asdf asdf as df asdf asd fas df",
      "date": 1569271191768,
      "listId": 1,
      "id": 83,
      "completed": false
    },
    {
      "name": "fasdf",
      "date": 1569405374161,
      "listId": 1,
      "completed": true,
      "id": 133
    },
    {
      "name": "33123",
      "date": 1569405560378,
      "listId": 1,
      "completed": true,
      "id": 134
    },
    {
      "name": "fsdfsd",
      "date": 1569405563866,
      "listId": 1,
      "completed": true,
      "id": 135
    },
    {
      "name": "asdfasd",
      "date": 1569406624361,
      "listId": 1,
      "completed": true,
      "id": 136
    },
    {
      "name": "fasdfsd",
      "date": 1569406629184,
      "listId": 1,
      "completed": true,
      "id": 137
    },
    {
      "name": "fasdf",
      "date": 1569406632504,
      "listId": 1,
      "completed": false,
      "id": 138
    },
    {
      "name": "igftu",
      "date": 1569424374868,
      "listId": 1,
      "completed": false,
      "id": 139
    }
  ]
}